pypianoroll/__init__.py
pypianoroll/core.py
pypianoroll/inputs.py
pypianoroll/metrics.py
pypianoroll/multitrack.py
pypianoroll/outputs.py
pypianoroll/track.py
pypianoroll/utils.py
pypianoroll/version.py
pypianoroll/visualization.py
pypianoroll-1.0.4.dist-info/LICENSE
pypianoroll-1.0.4.dist-info/METADATA
pypianoroll-1.0.4.dist-info/WHEEL
pypianoroll-1.0.4.dist-info/top_level.txt
pypianoroll-1.0.4.dist-info/RECORD
