Metadata-Version: 2.1
Name: pypianoroll
Version: 1.0.4
Summary: A toolkit for working with piano rolls
Home-page: UNKNOWN
Author: Hao-Wen Dong
Author-email: salu.hwdong@gmail.com
License: MIT
Download-URL: https://github.com/salu133445/pypianoroll/archive/v1.0.4.tar.gz
Project-URL: Documentation, https://salu133445.github.io/pypianoroll/
Keywords: music,audio,music-information-retrieval
Platform: UNKNOWN
Classifier: Development Status :: 5 - Production/Stable
Classifier: License :: OSI Approved :: MIT License
Classifier: Programming Language :: Python :: 3
Classifier: Topic :: Multimedia :: Sound/Audio
Requires-Python: >=3.6
Provides-Extra: test
